niftithings/__init__.py
niftithings/nifti.py
niftithings-0.2.1.dist-info/LICENSE
niftithings-0.2.1.dist-info/METADATA
niftithings-0.2.1.dist-info/WHEEL
niftithings-0.2.1.dist-info/top_level.txt
niftithings-0.2.1.dist-info/RECORD
