Metadata-Version: 2.2
Name: niftithings
Version: 0.2.1
Summary: A Python library for working with Nifti images.
Author-email: Jeroen Bertels <jeroen.bertels@gmail.com>
Project-URL: Homepage, https://github.com/JeroenBertels/niftithings
Classifier: Programming Language :: Python :: 3
Classifier: License :: OSI Approved :: Apache Software License
Classifier: Operating System :: OS Independent
Requires-Python: >=3.8
License-File: LICENSE
Requires-Dist: numpy
Requires-Dist: scipy
Requires-Dist: nibabel
Requires-Dist: arraythings
Requires-Dist: dicom2nifti
